dz_dynamodb/__init__.py
dz_dynamodb/deserialize.py
dz_dynamodb/discover.py
dz_dynamodb/dynamodb.py
dz_dynamodb/sync.py
dz_dynamodb/sync_strategies/__init__.py
dz_dynamodb/sync_strategies/full_table.py
dz_dynamodb/sync_strategies/log_based.py
sh_dynamodb/__init__.py
sh_dynamodb/deserialize.py
sh_dynamodb/discover.py
sh_dynamodb/dynamodb.py
sh_dynamodb/sync.py
sh_dynamodb/sync_strategies/__init__.py
sh_dynamodb/sync_strategies/full_table.py
sh_dynamodb/sync_strategies/log_based.py
sh_dynamodb-1.3.9.dist-info/LICENSE
sh_dynamodb-1.3.9.dist-info/METADATA
sh_dynamodb-1.3.9.dist-info/WHEEL
sh_dynamodb-1.3.9.dist-info/entry_points.txt
sh_dynamodb-1.3.9.dist-info/top_level.txt
sh_dynamodb-1.3.9.dist-info/RECORD
