Metadata-Version: 2.1
Name: sh-dynamodb
Version: 1.3.9
Summary: Singer.io tap for extracting data
Home-page: http://singer.io
Author: Stitch
License: UNKNOWN
Platform: UNKNOWN
Classifier: Programming Language :: Python :: 3 :: Only
License-File: LICENSE
Requires-Dist: boto3 ==1.14.9
Requires-Dist: singer-python ==5.9.0
Requires-Dist: terminaltables ==3.1.0
Requires-Dist: backoff ==1.8.0
Provides-Extra: dev
Requires-Dist: ipdb ; extra == 'dev'
Requires-Dist: pylint ; extra == 'dev'
Requires-Dist: nose ; extra == 'dev'
